{
  "version": "1.0.0",
  "name": "l2conceptv1",
  "instructions": [
    {
      "name": "initialize",
      "accounts": [
        { "name": "configAdmin", "isMut": true, "isSigner": true },
        { "name": "config", "isMut": true, "isSigner": false },
        { "name": "vaultAuthority", "isMut": true, "isSigner": false },
        { "name": "systemProgram", "isMut": false, "isSigner": false }
      ],
      "args": [
        { "name": "delegationProgramId", "type": { "option": "publicKey" } }
      ]
    },
    {
      "name": "join",
      "accounts": [
        { "name": "owner", "isMut": true, "isSigner": true },
        { "name": "userState", "isMut": true, "isSigner": false },
        { "name": "systemProgram", "isMut": false, "isSigner": false }
      ],
      "args": []
    },
    {
      "name": "addMint",
      "accounts": [
        { "name": "owner", "isMut": true, "isSigner": true },
        { "name": "mint", "isMut": false, "isSigner": false },
        { "name": "userState", "isMut": false, "isSigner": false },
        { "name": "userBalance", "isMut": true, "isSigner": false },
        { "name": "systemProgram", "isMut": false, "isSigner": false }
      ],
      "args": []
    },
    {
      "name": "deposit",
      "accounts": [
        { "name": "owner", "isMut": true, "isSigner": true },
        { "name": "userState", "isMut": true, "isSigner": false },
        { "name": "userBalance", "isMut": true, "isSigner": false },
        { "name": "mint", "isMut": false, "isSigner": false },
        { "name": "userAta", "isMut": true, "isSigner": false },
        { "name": "vaultAuthority", "isMut": false, "isSigner": false },
        { "name": "vaultAta", "isMut": true, "isSigner": false },
        { "name": "tokenProgram", "isMut": false, "isSigner": false },
        { "name": "associatedTokenProgram", "isMut": false, "isSigner": false },
        { "name": "systemProgram", "isMut": false, "isSigner": false },
        { "name": "rent", "isMut": false, "isSigner": false }
      ],
      "args": [{ "name": "amount", "type": "u64" }]
    },
    {
      "name": "transferBatch",
      "accounts": [
        { "name": "sender", "isMut": true, "isSigner": true },
        { "name": "senderUserState", "isMut": true, "isSigner": false },
        { "name": "senderBalance", "isMut": true, "isSigner": false },
        { "name": "mint", "isMut": false, "isSigner": false },
        { "name": "owner", "isMut": false, "isSigner": false }
      ],
      "args": [
        {
          "name": "items",
          "type": {
            "vec": {
              "defined": "TransferItem"
            }
          }
        }
      ]
    },
    {
      "name": "withdraw",
      "accounts": [
        { "name": "owner", "isMut": true, "isSigner": true },
        { "name": "userState", "isMut": true, "isSigner": false },
        { "name": "userBalance", "isMut": true, "isSigner": false },
        { "name": "mint", "isMut": false, "isSigner": false },
        { "name": "vaultAuthority", "isMut": false, "isSigner": false },
        { "name": "vaultAta", "isMut": true, "isSigner": false },
        { "name": "destinationAta", "isMut": true, "isSigner": false },
        { "name": "tokenProgram", "isMut": false, "isSigner": false }
      ],
      "args": [{ "name": "amount", "type": "u64" }]
    },
    {
      "name": "delegateUserStateAndBalances",
      "accounts": [
        { "name": "owner", "isMut": true, "isSigner": true },
        { "name": "userState", "isMut": true, "isSigner": false },
        { "name": "magicContext", "isMut": false, "isSigner": false },
        { "name": "magicProgram", "isMut": false, "isSigner": false },
        { "name": "systemProgram", "isMut": false, "isSigner": false }
      ],
      "args": [{ "name": "mintList", "type": { "vec": "publicKey" } }]
    },
    {
      "name": "commitAndUndelegateUserStateAndBalances",
      "accounts": [
        { "name": "payer", "isMut": true, "isSigner": true },
        { "name": "owner", "isMut": false, "isSigner": false },
        { "name": "userState", "isMut": true, "isSigner": false },
        { "name": "magicContext", "isMut": false, "isSigner": false },
        { "name": "magicProgram", "isMut": false, "isSigner": false },
        { "name": "systemProgram", "isMut": false, "isSigner": false }
      ],
      "args": [{ "name": "mintList", "type": { "vec": "publicKey" } }]
    }
  ],
  "accounts": [
    {
      "name": "Config",
      "type": {
        "kind": "struct",
        "fields": [
          { "name": "admin", "type": "publicKey" },
          { "name": "delegationProgramId", "type": "publicKey" },
          { "name": "bump", "type": "u8" }
        ]
      }
    },
    {
      "name": "UserState",
      "type": {
        "kind": "struct",
        "fields": [
          { "name": "owner", "type": "publicKey" },
          { "name": "bump", "type": "u8" },
          { "name": "stateVersion", "type": "u64" }
        ]
      }
    },
    {
      "name": "UserBalance",
      "type": {
        "kind": "struct",
        "fields": [
          { "name": "owner", "type": "publicKey" },
          { "name": "mint", "type": "publicKey" },
          { "name": "bump", "type": "u8" },
          { "name": "amount", "type": "u64" },
          { "name": "version", "type": "u64" }
        ]
      }
    },
    {
      "name": "VaultAuthority",
      "type": {
        "kind": "struct",
        "fields": [{ "name": "bump", "type": "u8" }]
      }
    }
  ],
  "types": [
    {
      "name": "TransferItem",
      "type": {
        "kind": "struct",
        "fields": [
          { "name": "toOwner", "type": "publicKey" },
          { "name": "amount", "type": "u64" }
        ]
      }
    }
  ],
  "events": [
    {
      "name": "InitializeEvent",
      "fields": [
        { "name": "admin", "type": "publicKey", "index": false },
        { "name": "delegationProgramId", "type": "publicKey", "index": false }
      ]
    },
    {
      "name": "JoinEvent",
      "fields": [{ "name": "owner", "type": "publicKey", "index": false }]
    },
    {
      "name": "AddMintEvent",
      "fields": [
        { "name": "owner", "type": "publicKey", "index": false },
        { "name": "mint", "type": "publicKey", "index": false }
      ]
    },
    {
      "name": "DepositEvent",
      "fields": [
        { "name": "owner", "type": "publicKey", "index": false },
        { "name": "mint", "type": "publicKey", "index": false },
        { "name": "amount", "type": "u64", "index": false },
        { "name": "newBalance", "type": "u64", "index": false },
        { "name": "stateVersion", "type": "u64", "index": false }
      ]
    },
    {
      "name": "TransferBatchEvent",
      "fields": [
        { "name": "fromOwner", "type": "publicKey", "index": false },
        { "name": "mint", "type": "publicKey", "index": false },
        { "name": "recipientCount", "type": "u16", "index": false },
        { "name": "totalAmount", "type": "u64", "index": false },
        { "name": "stateVersion", "type": "u64", "index": false }
      ]
    },
    {
      "name": "WithdrawEvent",
      "fields": [
        { "name": "owner", "type": "publicKey", "index": false },
        { "name": "mint", "type": "publicKey", "index": false },
        { "name": "amount", "type": "u64", "index": false },
        { "name": "newBalance", "type": "u64", "index": false },
        { "name": "stateVersion", "type": "u64", "index": false }
      ]
    },
    {
      "name": "DelegateEvent",
      "fields": [
        { "name": "owner", "type": "publicKey", "index": false },
        { "name": "mintCount", "type": "u8", "index": false },
        { "name": "mints", "type": { "vec": "publicKey" }, "index": false }
      ]
    },
    {
      "name": "CommitUndelegateEvent",
      "fields": [
        { "name": "owner", "type": "publicKey", "index": false },
        { "name": "mintCount", "type": "u8", "index": false },
        { "name": "mints", "type": { "vec": "publicKey" }, "index": false }
      ]
    }
  ],
  "errors": [
    { "code": 6000, "name": "NotInitialized", "msg": "Program not initialized" },
    { "code": 6001, "name": "NotJoined", "msg": "User has not joined" },
    { "code": 6002, "name": "BalanceNotFound", "msg": "Balance account not found" },
    { "code": 6003, "name": "InsufficientBalance", "msg": "Insufficient balance" },
    { "code": 6004, "name": "InvalidRecipientAccounts", "msg": "Invalid recipient accounts provided" },
    { "code": 6005, "name": "InvalidMint", "msg": "Invalid mint account" },
    { "code": 6006, "name": "InvalidAmount", "msg": "Invalid amount" },
    { "code": 6007, "name": "WithdrawWhileDelegated", "msg": "Withdrawal not allowed while account is delegated" },
    { "code": 6008, "name": "Overflow", "msg": "Arithmetic overflow" },
    { "code": 6009, "name": "Underflow", "msg": "Arithmetic underflow" },
    { "code": 6010, "name": "NotAuthorized", "msg": "Not authorized" },
    { "code": 6011, "name": "TooManyRecipients", "msg": "Too many recipients in batch transfer" },
    { "code": 6012, "name": "SelfTransferNotAllowed", "msg": "Self transfer not allowed" },
    { "code": 6013, "name": "DuplicateRecipient", "msg": "Duplicate recipient in batch transfer" },
    { "code": 6014, "name": "InvalidMintList", "msg": "Invalid mint list" },
    { "code": 6015, "name": "AlreadyDelegated", "msg": "Account is already delegated" },
    { "code": 6016, "name": "NotDelegated", "msg": "Account is not delegated" }
  ],
  "metadata": {
    "address": "L2CnccKT1qHNS1wJ7p3wJ3JhCX5s4J5wT5x3h5mH2j1"
  }
}
